ustash/__init__.py
ustash/py.typed
ustash-0.0.2.dist-info/LICENSE.txt
ustash-0.0.2.dist-info/METADATA
ustash-0.0.2.dist-info/WHEEL
ustash-0.0.2.dist-info/top_level.txt
ustash-0.0.2.dist-info/RECORD
